{
  "openapi": "3.0.1",
  "info": {
    "title": "WebApplication1",
    "version": "1.0"
  },
  "paths": {
    "/api/user": {
      "get": {
        "tags": [
          "user"
        ],
        "responses": {
          "200": {
            "description": "OK"
          }
        }
      },
      "post": {
        "tags": [
          "user"
        ],
        "requestBody": {
          "content": {
            "application/json": {
              "schema": {
                "$ref": "#/components/schemas/AddUserDto"
              }
            },
            "text/json": {
              "schema": {
                "$ref": "#/components/schemas/AddUserDto"
              }
            },
            "application/*+json": {
              "schema": {
                "$ref": "#/components/schemas/AddUserDto"
              }
            }
          }
        },
        "responses": {
          "200": {
            "description": "OK"
          }
        }
      }
    },
    "/api/user/{id}": {
      "put": {
        "tags": [
          "user"
        ],
        "parameters": [
          {
            "name": "id",
            "in": "path",
            "required": true,
            "schema": {
              "type": "integer",
              "format": "int32"
            }
          }
        ],
        "requestBody": {
          "content": {
            "application/json": {
              "schema": {
                "$ref": "#/components/schemas/AddUserDto"
              }
            },
            "text/json": {
              "schema": {
                "$ref": "#/components/schemas/AddUserDto"
              }
            },
            "application/*+json": {
              "schema": {
                "$ref": "#/components/schemas/AddUserDto"
              }
            }
          }
        },
        "responses": {
          "200": {
            "description": "OK"
          }
        }
      },
      "delete": {
        "tags": [
          "user"
        ],
        "parameters": [
          {
            "name": "id",
            "in": "path",
            "required": true,
            "schema": {
              "type": "integer",
              "format": "int32"
            }
          }
        ],
        "responses": {
          "200": {
            "description": "OK"
          }
        }
      }
    },
    "/api/user/search": {
      "get": {
        "tags": [
          "user"
        ],
        "parameters": [
          {
            "name": "keyword",
            "in": "query",
            "schema": {
              "type": "string"
            }
          }
        ],
        "responses": {
          "200": {
            "description": "OK"
          }
        }
      }
    }
  },
  "components": {
    "schemas": {
      "AddUserDto": {
        "required": [
          "email",
          "name"
        ],
        "type": "object",
        "properties": {
          "id": {
            "type": "integer",
            "format": "int32"
          },
          "name": {
            "minLength": 1,
            "type": "string"
          },
          "email": {
            "minLength": 1,
            "type": "string",
            "format": "email"
          },
          "age": {
            "type": "integer",
            "format": "int32"
          }
        },
        "additionalProperties": false
      }
    }
  }
}